orion_browser_mcp/__init__.py
orion_browser_mcp/__main__.py
orion_browser_mcp/browser_actions.py
orion_browser_mcp/browser_interface.py
orion_browser_mcp/config.py
orion_browser_mcp/example_usage.py
orion_browser_mcp/local_browser_service.py
orion_browser_mcp/remote_browser_service.py
orion_browser_mcp/utils.py
orion_browser_mcp/server/__init__.py
orion_browser_mcp/server/fast_server.py
orion_browser_mcp-0.4.7.dist-info/METADATA
orion_browser_mcp-0.4.7.dist-info/WHEEL
orion_browser_mcp-0.4.7.dist-info/entry_points.txt
orion_browser_mcp-0.4.7.dist-info/top_level.txt
orion_browser_mcp-0.4.7.dist-info/RECORD
