Metadata-Version: 2.4
Name: orion-browser-mcp
Version: 0.4.7
Summary: Orion Browser MCP服务
Requires-Python: >=3.12
Requires-Dist: mcp[cli]>=1.6.0
Requires-Dist: orion-browser==0.5.1
Requires-Dist: aiohttp>=3.9.0
Requires-Dist: typer>=0.15.2
Requires-Dist: starlette>=0.46.0
Requires-Dist: uvicorn>=0.34.0
Requires-Dist: pillow>=10.0.0
Requires-Dist: python-dotenv>=1.0.1
